odoo10_addon_l10n_ch_qr_bill_transaction_id-10.0.1.0.0.99.dev3-nspkg.pth
odoo/addons/l10n_ch_qr_bill_transaction_id/README.rst
odoo/addons/l10n_ch_qr_bill_transaction_id/__init__.py
odoo/addons/l10n_ch_qr_bill_transaction_id/__manifest__.py
odoo/addons/l10n_ch_qr_bill_transaction_id/i18n/l10n_ch_qr_bill_transaction_id.pot
odoo/addons/l10n_ch_qr_bill_transaction_id/models/__init__.py
odoo/addons/l10n_ch_qr_bill_transaction_id/models/account_invoice.py
odoo/addons/l10n_ch_qr_bill_transaction_id/static/description/icon.png
odoo/addons/l10n_ch_qr_bill_transaction_id/tests/__init__.py
odoo/addons/l10n_ch_qr_bill_transaction_id/tests/test_transaction_id.py
odoo10_addon_l10n_ch_qr_bill_transaction_id-10.0.1.0.0.99.dev3.dist-info/METADATA
odoo10_addon_l10n_ch_qr_bill_transaction_id-10.0.1.0.0.99.dev3.dist-info/WHEEL
odoo10_addon_l10n_ch_qr_bill_transaction_id-10.0.1.0.0.99.dev3.dist-info/namespace_packages.txt
odoo10_addon_l10n_ch_qr_bill_transaction_id-10.0.1.0.0.99.dev3.dist-info/top_level.txt
odoo10_addon_l10n_ch_qr_bill_transaction_id-10.0.1.0.0.99.dev3.dist-info/RECORD
