Metadata-Version: 2.1
Name: odoo10-addon-l10n-ch-qr-bill-transaction-id
Version: 10.0.1.0.0.99.dev3
Summary: Glue module with base_transaction_id
Home-page: https://github.com/OCA/l10n-switzerland
Author: Camptocamp,Odoo Community Association (OCA)
Author-email: support@odoo-community.org
License: LGPL-3
Platform: UNKNOWN
Classifier: Programming Language :: Python
Classifier: Framework :: Odoo
Classifier: License :: OSI Approved :: GNU Lesser General Public License v3 (LGPLv3)
Requires-Python: ~=2.7
Requires-Dist: odoo10-addon-base-transaction-id
Requires-Dist: odoo10-addon-l10n-ch-qr-bill
Requires-Dist: odoo (<10.1dev,>=10.0)
